shipmaster/cli/__init__.py
shipmaster/cli/cli.py
shipmaster-0.0.1.dist-info/DESCRIPTION.rst
shipmaster-0.0.1.dist-info/METADATA
shipmaster-0.0.1.dist-info/RECORD
shipmaster-0.0.1.dist-info/WHEEL
shipmaster-0.0.1.dist-info/entry_points.txt
shipmaster-0.0.1.dist-info/metadata.json
shipmaster-0.0.1.dist-info/top_level.txt
