Metadata-Version: 2.0
Name: shipmaster
Version: 0.0.1
Summary: Continuous integration and deployment.
Home-page: https://github.com/damoti/shipmaster
Author: Lex Berezhny
Author-email: lex@damoti.com
License: BSD
Keywords: ci deployment testing
Platform: UNKNOWN
Classifier: Intended Audience :: Developers
Classifier: License :: OSI Approved :: BSD License
Classifier: Programming Language :: Python :: 3
Classifier: Topic :: Software Development :: Testing
Requires-Dist: docker-compose
Requires-Dist: humanfriendly
Requires-Dist: ruamel.yaml
